temp_michprev_bar/__init__.py
temp_michprev_bar-0.1.0.dist-info/METADATA
temp_michprev_bar-0.1.0.dist-info/WHEEL
temp_michprev_bar-0.1.0.dist-info/RECORD
