Metadata-Version: 2.1
Name: temp-michprev-bar
Version: 0.1.0
Summary: 
Author: Michal Převrátil
Author-email: michprev@gmail.com
Requires-Python: >=3.11,<4.0
Classifier: Programming Language :: Python :: 3
Classifier: Programming Language :: Python :: 3.11
Requires-Dist: temp-michprev-foo (==0.1.0)
